FolderProcessing/__init__.py
FolderProcessing/file.py
FolderProcessing/new.py
FolderProcessing/openfile.py
FolderProcessing/seefile.py
FolderProcessing/view.py
FolderProcessing-0.1.1.2.dist-info/LICENSE.txt
FolderProcessing-0.1.1.2.dist-info/METADATA
FolderProcessing-0.1.1.2.dist-info/WHEEL
FolderProcessing-0.1.1.2.dist-info/top_level.txt
FolderProcessing-0.1.1.2.dist-info/RECORD
