Metadata-Version: 2.1
Name: FolderProcessing
Version: 0.1.1.2
Summary: 一个基于其他模块，快速执行文件夹处理的模块|A module that quickly performs folder processing based on other modules
Home-page: https://codechina.csdn.net/qq_53280175/folderprocessing
Author: PYmili
Author-email: mc2005wj@163.com
Maintainer: PYmili
Maintainer-email: mc2005wj@163.com
License: MIT License
Platform: UNKNOWN
Classifier: Operating System :: OS Independent
Classifier: Natural Language :: Chinese (Simplified)
Classifier: Natural Language :: English
Classifier: License :: OSI Approved :: MIT License
Classifier: Programming Language :: Python :: 3.6
Classifier: Programming Language :: Python :: 3.7
Classifier: Programming Language :: Python :: 3.8
Classifier: Programming Language :: Python :: 3.9
Classifier: Topic :: Software Development :: Libraries
Requires-Python: >=3.7
License-File: LICENSE.txt
